{
  "meta": {
    "version": "2.0.0",
    "title": "Daily Reflection Tree",
    "axes": [
      "locus",
      "orientation",
      "radius"
    ],
    "total_nodes": 28,
    "entry_node": "START",
    "profiles": 8
  },
  "nodes": {
    "START": {
      "id": "START",
      "type": "start",
      "text": "End of day. Let's look at it.",
      "next": "Q1"
    },
    "Q1": {
      "id": "Q1",
      "type": "question",
      "axis": "locus",
      "text": "Something didn't go the way you wanted today. Before you had time to think about it — what was your first instinct?",
      "options": [
        {
          "key": "A",
          "text": "To figure out what I missed or did wrong.",
          "classification": "INTERNAL",
          "next": "Q2_I"
        },
        {
          "key": "B",
          "text": "To think about what made it harder than it needed to be.",
          "classification": "EXTERNAL",
          "next": "Q2_E"
        },
        {
          "key": "C",
          "text": "To wonder whether it was even a fair situation to be in.",
          "classification": "EXTERNAL",
          "next": "Q2_E"
        },
        {
          "key": "D",
          "text": "To move past it and focus on what was next.",
          "classification": "INTERNAL",
          "next": "Q2_I"
        }
      ],
      "signal": null
    },
    "Q2_I": {
      "id": "Q2_I",
      "type": "question",
      "axis": "locus",
      "branch_condition": "Q1 IN [A, D]",
      "text": "When you hit an obstacle you didn't anticipate today, what did you actually do?",
      "options": [
        {
          "key": "A",
          "text": "Adapted — figured out a workaround or changed my approach.",
          "classification": "INTERNAL_DEEP",
          "next": "REFLECT_LOCUS_INT",
          "stores": "locus_depth"
        },
        {
          "key": "B",
          "text": "Pushed through — kept doing what I was doing but harder.",
          "classification": "INTERNAL_SHALLOW",
          "next": "REFLECT_LOCUS_INT",
          "stores": "locus_depth"
        },
        {
          "key": "C",
          "text": "Paused — asked for input before deciding how to move.",
          "classification": "INTERNAL_DEEP",
          "next": "REFLECT_LOCUS_INT",
          "stores": "locus_depth"
        },
        {
          "key": "D",
          "text": "Noted it — didn't address it yet but plan to.",
          "classification": "INTERNAL_SHALLOW",
          "next": "REFLECT_LOCUS_INT",
          "stores": "locus_depth"
        }
      ],
      "signal": "locus:internal"
    },
    "Q2_E": {
      "id": "Q2_E",
      "type": "question",
      "axis": "locus",
      "branch_condition": "Q1 IN [B, C]",
      "text": "When you think about what made today harder — how clearly can you name it right now?",
      "options": [
        {
          "key": "A",
          "text": "Completely clearly — I can name exactly what or who the blocker was.",
          "classification": "EXTERNAL_CONCRETE",
          "next": "REFLECT_LOCUS_EXT",
          "stores": "locus_depth"
        },
        {
          "key": "B",
          "text": "Somewhat — I know something was off but not precisely what.",
          "classification": "EXTERNAL_DIFFUSE",
          "next": "REFLECT_LOCUS_EXT",
          "stores": "locus_depth"
        },
        {
          "key": "C",
          "text": "Vaguely — it just felt like friction without a specific cause.",
          "classification": "EXTERNAL_DIFFUSE",
          "next": "REFLECT_LOCUS_EXT",
          "stores": "locus_depth"
        },
        {
          "key": "D",
          "text": "I'd rather not examine it today.",
          "classification": "EXTERNAL_AVOIDANT",
          "next": "REFLECT_LOCUS_EXT",
          "stores": "locus_depth"
        }
      ],
      "signal": "locus:external"
    },
    "REFLECT_LOCUS_INT": {
      "id": "REFLECT_LOCUS_INT",
      "type": "reflection",
      "axis": "locus",
      "text": "You went looking for your own hand in what happened. That's not self-blame — it's the starting position for anyone who wants to learn from a day rather than just survive it.",
      "next": "BRIDGE_1_2"
    },
    "REFLECT_LOCUS_EXT": {
      "id": "REFLECT_LOCUS_EXT",
      "type": "reflection",
      "axis": "locus",
      "text": "When things go sideways, attention goes outward first. That's a real response to a real situation. Somewhere in there, though, you made at least one call. You don't have to find it tonight.",
      "next": "BRIDGE_1_2"
    },
    "BRIDGE_1_2": {
      "id": "BRIDGE_1_2",
      "type": "bridge",
      "text": "Now let's shift — from how you handled things, to what you were oriented toward.",
      "next": "Q3"
    },
    "Q3": {
      "id": "Q3",
      "type": "question",
      "axis": "orientation",
      "text": "Pick something you actually finished today — anything. Not the most important thing. Just something done. What crosses your mind when you look at it now?",
      "options": [
        {
          "key": "A",
          "text": "Whether it actually moved something forward for someone.",
          "classification": "CONTRIBUTION",
          "next": "Q4_C"
        },
        {
          "key": "B",
          "text": "That it's done — there's a real satisfaction in closing things out.",
          "classification": "ENTITLEMENT_SHALLOW",
          "next": "Q4_E"
        },
        {
          "key": "C",
          "text": "Whether anyone noticed, or will.",
          "classification": "ENTITLEMENT_RECOGNITION",
          "next": "Q4_E"
        },
        {
          "key": "D",
          "text": "What it unlocks or enables next.",
          "classification": "CONTRIBUTION",
          "next": "Q4_C"
        }
      ],
      "signal": null
    },
    "Q4_C": {
      "id": "Q4_C",
      "type": "question",
      "axis": "orientation",
      "branch_condition": "Q3 IN [A, D]",
      "text": "When your work creates value for others — how does that actually affect your sense of whether the day was worth it?",
      "options": [
        {
          "key": "A",
          "text": "It's the primary measure. Without that, even a productive day feels hollow.",
          "classification": "CONTRIBUTION_DEEP",
          "next": "REFLECT_ORIENT_C",
          "stores": "orient_depth"
        },
        {
          "key": "B",
          "text": "It matters, but I also need to feel personally satisfied with the quality.",
          "classification": "CONTRIBUTION_BALANCED",
          "next": "REFLECT_ORIENT_C",
          "stores": "orient_depth"
        },
        {
          "key": "C",
          "text": "It depends on who benefited — some people matter more to me than others.",
          "classification": "CONTRIBUTION_SELECTIVE",
          "next": "REFLECT_ORIENT_C",
          "stores": "orient_depth"
        },
        {
          "key": "D",
          "text": "I don't think about it that way — I just focus on the work itself.",
          "classification": "CONTRIBUTION_INTRINSIC",
          "next": "REFLECT_ORIENT_C",
          "stores": "orient_depth"
        }
      ],
      "signal": "orientation:contribution"
    },
    "Q4_E": {
      "id": "Q4_E",
      "type": "question",
      "axis": "orientation",
      "branch_condition": "Q3 IN [B, C]",
      "text": "When you think about what you're owed for your effort today — recognition, opportunity, a clearer path — where are you?",
      "options": [
        {
          "key": "A",
          "text": "Not thinking about it — I'm focused on what I'm building.",
          "classification": "ENTITLEMENT_LOW",
          "next": "REFLECT_ORIENT_E",
          "stores": "orient_depth"
        },
        {
          "key": "B",
          "text": "There's a gap between what I've contributed and what I've received.",
          "classification": "ENTITLEMENT_PERCEIVED_GAP",
          "next": "REFLECT_ORIENT_E",
          "stores": "orient_depth"
        },
        {
          "key": "C",
          "text": "I've been doing more than others at this level and it hasn't been noticed.",
          "classification": "ENTITLEMENT_COMPARATIVE",
          "next": "REFLECT_ORIENT_E",
          "stores": "orient_depth"
        },
        {
          "key": "D",
          "text": "I deserve a clearer path forward and haven't been given one.",
          "classification": "ENTITLEMENT_FRUSTRATED",
          "next": "REFLECT_ORIENT_E",
          "stores": "orient_depth"
        }
      ],
      "signal": "orientation:entitlement"
    },
    "REFLECT_ORIENT_C": {
      "id": "REFLECT_ORIENT_C",
      "type": "reflection",
      "axis": "orientation",
      "text": "You're measuring today by what it moved for someone else. That's not a given — most people measure by what got finished, what got recognized, or what got them further along.",
      "next": "BRIDGE_2_3"
    },
    "REFLECT_ORIENT_E": {
      "id": "REFLECT_ORIENT_E",
      "type": "reflection",
      "axis": "orientation",
      "text": "You're aware of what the day cost you relative to what it gave back. That accounting is worth doing honestly — it tells you something about where you are, not just what happened.",
      "next": "BRIDGE_2_3"
    },
    "BRIDGE_2_3": {
      "id": "BRIDGE_2_3",
      "type": "bridge",
      "text": "Last axis. This one's about range — how wide your awareness actually was today.",
      "next": "Q5"
    },
    "Q5": {
      "id": "Q5",
      "type": "question",
      "axis": "radius",
      "text": "Right now, at the end of the day — who else is in the room in your head?",
      "options": [
        {
          "key": "A",
          "text": "Someone specific — a person I'm still thinking about.",
          "classification": "OTHERS_SPECIFIC",
          "next": "Q6_HIGH"
        },
        {
          "key": "B",
          "text": "The team in some general sense — I'm tracking how we're doing.",
          "classification": "OTHERS_TEAM",
          "next": "Q6_HIGH"
        },
        {
          "key": "C",
          "text": "Mostly just me. I needed the focus, and I'm okay with that.",
          "classification": "SELF_ACKNOWLEDGED",
          "next": "Q6_LOW"
        },
        {
          "key": "D",
          "text": "No one, really. Today was heads-down and that's how it is.",
          "classification": "SELF_UNAWARE",
          "next": "Q6_LOW"
        }
      ],
      "signal": null
    },
    "Q6_HIGH": {
      "id": "Q6_HIGH",
      "type": "question",
      "axis": "radius",
      "branch_condition": "Q5 IN [A, B]",
      "text": "When you noticed someone else having a hard time today — what did you actually do with that?",
      "options": [
        {
          "key": "A",
          "text": "Acted on it — checked in, offered something, adjusted.",
          "classification": "RADIUS_ACTIVE",
          "next": "REFLECT_RADIUS_HIGH",
          "stores": "radius_depth"
        },
        {
          "key": "B",
          "text": "Held it — I was aware but deliberate about when and how to engage.",
          "classification": "RADIUS_DELIBERATE",
          "next": "REFLECT_RADIUS_HIGH",
          "stores": "radius_depth"
        },
        {
          "key": "C",
          "text": "Noted it — intended to follow up but didn't get there.",
          "classification": "RADIUS_PASSIVE",
          "next": "REFLECT_RADIUS_HIGH",
          "stores": "radius_depth"
        },
        {
          "key": "D",
          "text": "I don't have a consistent pattern here.",
          "classification": "RADIUS_UNCERTAIN",
          "next": "REFLECT_RADIUS_HIGH",
          "stores": "radius_depth"
        }
      ],
      "signal": "radius:high"
    },
    "Q6_LOW": {
      "id": "Q6_LOW",
      "type": "question",
      "axis": "radius",
      "branch_condition": "Q5 IN [C, D]",
      "text": "When you reflect on a day where you were very focused on your own work — what's the texture of that?",
      "options": [
        {
          "key": "A",
          "text": "Useful — I got a lot done and I needed that concentrated time.",
          "classification": "SELF_JUSTIFIED",
          "next": "REFLECT_RADIUS_LOW",
          "stores": "radius_depth"
        },
        {
          "key": "B",
          "text": "Slightly uncomfortable — I wonder if I missed something important.",
          "classification": "SELF_REFLECTIVE",
          "next": "REFLECT_RADIUS_LOW",
          "stores": "radius_depth"
        },
        {
          "key": "C",
          "text": "Normal — most of my days look like this and I don't question it.",
          "classification": "SELF_DEFAULT",
          "next": "REFLECT_RADIUS_LOW",
          "stores": "radius_depth"
        },
        {
          "key": "D",
          "text": "Relieving — less input from others means less complexity.",
          "classification": "SELF_PROTECTIVE",
          "next": "REFLECT_RADIUS_LOW",
          "stores": "radius_depth"
        }
      ],
      "signal": "radius:low"
    },
    "REFLECT_RADIUS_HIGH": {
      "id": "REFLECT_RADIUS_HIGH",
      "type": "reflection",
      "axis": "radius",
      "text": "You carried someone else today — in your awareness, at minimum. That's not nothing. Whether it turned into action is a separate question.",
      "next": "DECISION_FINAL"
    },
    "REFLECT_RADIUS_LOW": {
      "id": "REFLECT_RADIUS_LOW",
      "type": "reflection",
      "axis": "radius",
      "text": "Today was contained. Just you, your work, your own field of view. Some days that's a choice. Some days it's a default. Worth knowing which one this was.",
      "next": "DECISION_FINAL"
    },
    "DECISION_FINAL": {
      "id": "DECISION_FINAL",
      "type": "decision",
      "text": null,
      "routes": [
        {
          "condition": "locus==INTERNAL AND orientation==CONTRIBUTION AND radius==HIGH",
          "next": "SUMMARY_ICH"
        },
        {
          "condition": "locus==INTERNAL AND orientation==CONTRIBUTION AND radius==LOW",
          "next": "SUMMARY_ICL"
        },
        {
          "condition": "locus==INTERNAL AND orientation==ENTITLEMENT AND radius==HIGH",
          "next": "SUMMARY_IEH"
        },
        {
          "condition": "locus==INTERNAL AND orientation==ENTITLEMENT AND radius==LOW",
          "next": "SUMMARY_IEL"
        },
        {
          "condition": "locus==EXTERNAL AND orientation==CONTRIBUTION AND radius==HIGH",
          "next": "SUMMARY_ECH"
        },
        {
          "condition": "locus==EXTERNAL AND orientation==CONTRIBUTION AND radius==LOW",
          "next": "SUMMARY_ECL"
        },
        {
          "condition": "locus==EXTERNAL AND orientation==ENTITLEMENT AND radius==HIGH",
          "next": "SUMMARY_EEH"
        },
        {
          "condition": "locus==EXTERNAL AND orientation==ENTITLEMENT AND radius==LOW",
          "next": "SUMMARY_EEL"
        }
      ]
    },
    "SUMMARY_ICH": {
      "id": "SUMMARY_ICH",
      "type": "summary",
      "profile_key": "INTERNAL+CONTRIBUTION+HIGH",
      "title": "The Integrated Agent",
      "tags": [
        "INTERNAL",
        "CONTRIBUTION",
        "HIGH RADIUS"
      ],
      "text": "You took responsibility for what went wrong, measured your work by what it did for someone else, and kept other people in your field of awareness. That combination is rarer than it sounds — most people do one or two of those on any given day.\n\nThe version of this that goes wrong looks like someone so calibrated to others that their own signal gets lost in the noise. You probably don't have that problem, but it's worth checking: when you're reading the room, are you also in it?\n\nWhat would you still do tomorrow if no one were paying attention?",
      "depth_modifiers": "see modifiers table",
      "next": "END"
    },
    "SUMMARY_ICL": {
      "id": "SUMMARY_ICL",
      "type": "summary",
      "profile_key": "INTERNAL+CONTRIBUTION+LOW",
      "title": "The Productive Isolate",
      "tags": [
        "INTERNAL",
        "CONTRIBUTION",
        "LOW RADIUS"
      ],
      "text": "You took ownership of today and thought about impact — but the day was mostly yours. Not in an avoidant way; just contained. The work moved forward on your terms, in your space, toward something you believe in.\n\nThe risk here isn't low performance — it's miscalibration. You can be producing real value and still be misaligned with what the team or the organization actually needs, and not find out for a long time because you're not in a position to hear it.\n\nHigh-quality output in a closed loop is still a closed loop.",
      "depth_modifiers": "see modifiers table",
      "next": "END"
    },
    "SUMMARY_IEH": {
      "id": "SUMMARY_IEH",
      "type": "summary",
      "profile_key": "INTERNAL+ENTITLEMENT+HIGH",
      "title": "The Aware Deficit Tracker",
      "tags": [
        "INTERNAL",
        "ENTITLEMENT",
        "HIGH RADIUS"
      ],
      "text": "You saw other people today — probably clearly — and you also felt the gap between what you've put in and what you've gotten back. Those two things coexist without contradiction; awareness of others doesn't automatically produce satisfaction with your situation.\n\nThe pattern to watch: when the deficit becomes the dominant frame, social awareness becomes a form of scorekeeping — who got recognized, who didn't, who got the opportunity. That's not cynicism. It's a coherent response to an environment you've correctly diagnosed. But diagnosis without traction turns into inventory.\n\nWhat would you do with this situation if you stopped waiting for someone to notice the gap?",
      "depth_modifiers": "see modifiers table",
      "next": "END"
    },
    "SUMMARY_IEL": {
      "id": "SUMMARY_IEL",
      "type": "summary",
      "profile_key": "INTERNAL+ENTITLEMENT+LOW",
      "title": "The Self-Referential Agent",
      "tags": [
        "INTERNAL",
        "ENTITLEMENT",
        "LOW RADIUS"
      ],
      "text": "You owned today. Took responsibility. But the frame was almost entirely yours — your trajectory, your standards, your assessment of how you performed. The day wasn't about others, and you didn't sit in a posture of waiting to be rewarded. It was simply about you doing the work you're trying to do.\n\nThat's a disciplined and often productive state. It can also be a form of insulation — against feedback, against the messiness of actually needing others, against the possibility that your definition of 'good work' and theirs are different.\n\nSelf-accountability that doesn't include others isn't accountability — it's preference management.",
      "depth_modifiers": "see modifiers table",
      "next": "END"
    },
    "SUMMARY_ECH": {
      "id": "SUMMARY_ECH",
      "type": "summary",
      "profile_key": "EXTERNAL+CONTRIBUTION+HIGH",
      "title": "The Generous Attributor",
      "tags": [
        "EXTERNAL",
        "CONTRIBUTION",
        "HIGH RADIUS"
      ],
      "text": "You were oriented toward impact and aware of the people around you — both genuinely hard to do under friction. But when something went wrong today, the causation pointed outward. That's a real asymmetry: you assign ownership of value creation internally, but ownership of setbacks goes external.\n\nThe asymmetry isn't dishonest — it may be accurate. But contribution-oriented people who consistently attribute setbacks to external causes tend, over time, to become frustrated. They're giving a lot, they see the people they're serving, and they watch obstacles pile up in a space they feel they can't touch.\n\nWhat would change if you treated the obstacles as part of the work, not interruptions to it?",
      "depth_modifiers": "see modifiers table",
      "next": "END"
    },
    "SUMMARY_ECL": {
      "id": "SUMMARY_ECL",
      "type": "summary",
      "profile_key": "EXTERNAL+CONTRIBUTION+LOW",
      "title": "The Disconnected Contributor",
      "tags": [
        "EXTERNAL",
        "CONTRIBUTION",
        "LOW RADIUS"
      ],
      "text": "You intended impact today — the framing was outward — but you were largely heads-down, and when something went wrong, the cause was somewhere else. The combination produces a particular kind of frustration: you're trying to contribute, the environment keeps getting in the way, and you're too deep in the work to notice whether you're actually landing.\n\nThis isn't a character problem. It's a feedback problem. You don't have enough signal about whether what you're doing is connecting with anyone — because you're not in a position to receive it.\n\nContribution without calibration eventually becomes effort without direction.",
      "depth_modifiers": "see modifiers table",
      "next": "END"
    },
    "SUMMARY_EEH": {
      "id": "SUMMARY_EEH",
      "type": "summary",
      "profile_key": "EXTERNAL+ENTITLEMENT+HIGH",
      "title": "The Sensitized Observer",
      "tags": [
        "EXTERNAL",
        "ENTITLEMENT",
        "HIGH RADIUS"
      ],
      "text": "You read the room well today — saw people, tracked dynamics, understood what was happening around you. And you felt something was owed that hasn't arrived. What's notable is the combination: high perceptual accuracy, low sense of personal leverage.\n\nThis is often a correct diagnosis of a genuinely unfair situation. It's also a state that tends to be self-reinforcing — sharp perception of what's wrong, without the internal framing to see where you have any hand in changing it, produces increasingly detailed evidence of a problem you can't solve.\n\nWhat you can see precisely, you can't always fix. But the question is whether that stops at diagnosis.",
      "depth_modifiers": "see modifiers table",
      "next": "END"
    },
    "SUMMARY_EEL": {
      "id": "SUMMARY_EEL",
      "type": "summary",
      "profile_key": "EXTERNAL+ENTITLEMENT+LOW",
      "title": "The Closed Circuit",
      "tags": [
        "EXTERNAL",
        "ENTITLEMENT",
        "LOW RADIUS"
      ],
      "text": "The day happened to you, and you were mostly thinking about your own position in it. There's no aggression in that — it's just what the day looked like. Setbacks came from outside, work was about you, and other people existed at the periphery.\n\nThis is the state most resistant to reflection — not because you're unwilling, but because the feedback loops are self-confirming. External causation means nothing is yours to change. Self-focus means the signal from others doesn't arrive. Without either, there's nothing for today's reflection to act on.\n\nWhen everything happens to you and everything is about you — what would it even mean for something to be your fault?",
      "depth_modifiers": "see modifiers table",
      "next": "END"
    },
    "END": {
      "id": "END",
      "type": "end",
      "text": "See you tomorrow.",
      "next": null
    }
  },
  "depth_modifiers": {
    "locus": {
      "INTERNAL_DEEP": null,
      "INTERNAL_SHALLOW": "Note: you persisted today rather than adapted. Those aren't the same thing.",
      "EXTERNAL_CONCRETE": null,
      "EXTERNAL_DIFFUSE": "The obstacle you felt today didn't have a clear shape. That makes it harder to do anything about — and easier to carry forward.",
      "EXTERNAL_AVOIDANT": "You'd rather not look at it today. That's a valid response to a hard day. It's also how patterns become invisible."
    },
    "orientation": {
      "CONTRIBUTION_DEEP": null,
      "CONTRIBUTION_BALANCED": null,
      "CONTRIBUTION_SELECTIVE": "Your contribution orientation is conditional — some people count more than others. That's honest to say. It's also worth knowing.",
      "CONTRIBUTION_INTRINSIC": "Your orientation is toward craft, not impact. That's a legitimate way to work. It's also a different thing than contribution.",
      "ENTITLEMENT_LOW": null,
      "ENTITLEMENT_PERCEIVED_GAP": "You've calculated a gap between effort and return. The calculation may be accurate. But living inside it is a choice.",
      "ENTITLEMENT_COMPARATIVE": "You're measuring your position against others'. That comparison will never close — someone will always have gotten more.",
      "ENTITLEMENT_FRUSTRATED": "You want a clearer path and haven't been given one. That frustration is real. It's also preventing you from building one."
    },
    "radius": {
      "RADIUS_ACTIVE": null,
      "RADIUS_DELIBERATE": null,
      "RADIUS_PASSIVE": "You noticed, and you meant to follow up. The gap between noticing and acting is where most relational debt accumulates.",
      "RADIUS_UNCERTAIN": "You don't have a consistent pattern here. Inconsistency in this domain usually means you're reacting to your own state, not responding to theirs.",
      "SELF_JUSTIFIED": null,
      "SELF_REFLECTIVE": "The discomfort you felt about being inward-facing is the most useful thing in today's session. Follow it.",
      "SELF_DEFAULT": "Most of your days look like this and you don't question it. That sentence is worth questioning.",
      "SELF_PROTECTIVE": "You felt relief when others weren't in the mix. Worth sitting with — not as a judgment, just as a fact about how you're wired right now."
    }
  },
  "state_schema": {
    "locus": [
      "INTERNAL",
      "EXTERNAL"
    ],
    "locus_depth": [
      "INTERNAL_DEEP",
      "INTERNAL_SHALLOW",
      "EXTERNAL_CONCRETE",
      "EXTERNAL_DIFFUSE",
      "EXTERNAL_AVOIDANT"
    ],
    "orientation": [
      "CONTRIBUTION",
      "ENTITLEMENT"
    ],
    "orient_depth": [
      "CONTRIBUTION_DEEP",
      "CONTRIBUTION_BALANCED",
      "CONTRIBUTION_SELECTIVE",
      "CONTRIBUTION_INTRINSIC",
      "ENTITLEMENT_LOW",
      "ENTITLEMENT_PERCEIVED_GAP",
      "ENTITLEMENT_COMPARATIVE",
      "ENTITLEMENT_FRUSTRATED"
    ],
    "radius": [
      "HIGH",
      "LOW"
    ],
    "radius_depth": [
      "RADIUS_ACTIVE",
      "RADIUS_DELIBERATE",
      "RADIUS_PASSIVE",
      "RADIUS_UNCERTAIN",
      "SELF_JUSTIFIED",
      "SELF_REFLECTIVE",
      "SELF_DEFAULT",
      "SELF_PROTECTIVE"
    ],
    "answers": "dict keyed by node_id"
  }
}